pymedphys_dicom/__init__.py
pymedphys_dicom/_install_requires.py
pymedphys_dicom/_version.py
pymedphys_dicom/constants/__init__.py
pymedphys_dicom/constants/baseline_dicom_dictionary.json
pymedphys_dicom/constants/baseline_repeaters_dictionary.json
pymedphys_dicom/constants/core.py
pymedphys_dicom/constants/uuid.py
pymedphys_dicom/ct/__init__.py
pymedphys_dicom/ct/extend.py
pymedphys_dicom/delivery/__init__.py
pymedphys_dicom/delivery/core.py
pymedphys_dicom/delivery/utilities.py
pymedphys_dicom/dicom/__init__.py
pymedphys_dicom/dicom/anonymise.py
pymedphys_dicom/dicom/collection.py
pymedphys_dicom/dicom/coords.py
pymedphys_dicom/dicom/create.py
pymedphys_dicom/dicom/dose.py
pymedphys_dicom/dicom/header.py
pymedphys_dicom/dicom/identifying_keywords.json
pymedphys_dicom/dicom/structure.py
pymedphys_dicom/rtplan/__init__.py
pymedphys_dicom/rtplan/adjust.py
pymedphys_dicom/rtplan/build.py
pymedphys_dicom/rtplan/core.py
pymedphys_dicom/shim/__init__.py
pymedphys_dicom/utilities/__init__.py
pymedphys_dicom/utilities/files.py
pymedphys_dicom-0.11.0.dist-info/LICENSE-AGPL-3.0-or-later
pymedphys_dicom-0.11.0.dist-info/LICENSE-Apache-2.0
pymedphys_dicom-0.11.0.dist-info/METADATA
pymedphys_dicom-0.11.0.dist-info/WHEEL
pymedphys_dicom-0.11.0.dist-info/top_level.txt
pymedphys_dicom-0.11.0.dist-info/RECORD
